risingwave/__init__.py
risingwave/test_udf.py
risingwave/udf.py
risingwave/udf/health_check.py
risingwave-0.1.1.dist-info/METADATA
risingwave-0.1.1.dist-info/WHEEL
risingwave-0.1.1.dist-info/top_level.txt
risingwave-0.1.1.dist-info/RECORD
