Metadata-Version: 2.1
Name: risingwave
Version: 0.1.1
Summary: RisingWave Python API
Author: RisingWave Labs
License: Apache Software License
Classifier: Programming Language :: Python
Classifier: License :: OSI Approved :: Apache Software License
Requires-Python: >=3.8
Requires-Dist: pyarrow
Provides-Extra: test
Requires-Dist: pytest ; extra == 'test'
